tmprc/__init__.py
tmprc/runner.py
tmprc-0.1.2.dist-info/WHEEL
tmprc-0.1.2.dist-info/METADATA
tmprc-0.1.2.dist-info/RECORD
