Metadata-Version: 2.1
Name: tmprc
Version: 0.1.2
Summary: 
Home-page: https://github.com/runcode-io/runcode-python
License: MIT
Keywords: runcode
Author: subbarayudu
Author-email: subbarayudu@micropyramid.com
Requires-Python: >=3.8,<4.0
Classifier: License :: OSI Approved :: MIT License
Classifier: Programming Language :: Python :: 3
Classifier: Programming Language :: Python :: 3.10
Classifier: Programming Language :: Python :: 3.8
Classifier: Programming Language :: Python :: 3.9
Requires-Dist: requests (>=2.26.0,<3.0.0)
Project-URL: Repository, https://github.com/runcode-io/runcode-python
